setup.py
jz/__init__.py
jz.magic.egg-info/PKG-INFO
jz.magic.egg-info/SOURCES.txt
jz.magic.egg-info/dependency_links.txt
jz.magic.egg-info/namespace_packages.txt
jz.magic.egg-info/requires.txt
jz.magic.egg-info/top_level.txt
jz/magic/__init__.py
jz/magic/configure.zcml
jz/magic/interfaces.py
jz/magic/jz.magic-configure.zcml
jz/magic/jz.magic-meta.zcml
jz/magic/meta.zcml
jz/magic/readme.txt
jz/magic/utility.py
jz/magic/tests/__init__.py
jz/magic/tests/test_imagic.py
jz/magic/tests/test_utility.py
