Metadata-Version: 1.0
Name: jz.magic
Version: 0.1
Summary: Utility interface to magic python module.
Home-page: http://www.jellofishi.com/zope
Author: Gabi Shaar
Author-email: gabi@jbox-comp.com
License: GPL
Platform: UNKNOWN
